[
  {
    "tag_name": "entity",
    "ids_to_tags": {
      "1": "B-product",
      "2": "I-product",
      "3": "L-product",
      "4": "U-product",
      "5": "B-product_id",
      "6": "I-product_id",
      "7": "L-product_id",
      "8": "U-product_id",
      "0": "O"
    },
    "tags_to_ids": {
      "B-product": 1,
      "I-product": 2,
      "L-product": 3,
      "U-product": 4,
      "B-product_id": 5,
      "I-product_id": 6,
      "L-product_id": 7,
      "U-product_id": 8,
      "O": 0
    },
    "num_tags": 9
  }
]